utilsz/__init__.py
utilsz/__version__.py
utilsz/csv_util.py
utilsz/email_util.py
utilsz/excel_util.py
utilsz/file_util.py
utilsz/json_util.py
utilsz/list_util.py
utilsz/logging_util.py
utilsz/module_util.py
utilsz/requests_util.py
utilsz/scheduler_util.py
utilsz/str_util.py
utilsz/time_util.py
utilsz/url_util.py
utilsz/wecom_util.py
utilsz-0.1.3.dist-info/METADATA
utilsz-0.1.3.dist-info/WHEEL
utilsz-0.1.3.dist-info/top_level.txt
utilsz-0.1.3.dist-info/RECORD
